{"RecommendedArea":{"RecommendedString":"Προτεινόμενα"},"SubstrateRecommendations":{"TimestampNow":"Τώρα","TimestampSecondsAgo":"Πριν από {{seconds}}δευτερόλεπτα","TimestampMinutesAgo":"Πριν από {{minutes}}λεπτά","TimestampHoursAgo":"Πριν από {{hours}}ώρες","TimestampYesterday":"Χθες στις {{time}}","TimeStampDayAtTime":"{{date}} στις {{time}}"},"NoTopLevelSuggestionsText":{"NoTopLevelSuggestions_AppsAndFilesEnabled":"Όσο περισσότερο χρησιμοποιείτε τη συσκευή σας, τόσο περισσότερο θα εμφανίζουμε τα πρόσφατα αρχεία και τις νέες εφαρμογές σας εδώ.","NoTopLevelSuggestions_AppsEnabled":"Όσο περισσότερο χρησιμοποιείτε τη συσκευή σας, τόσο περισσότερο θα εμφανίζουμε τις νέες εφαρμογές σας εδώ.","NoTopLevelSuggestions_FilesEnabled":"Όσο περισσότερο χρησιμοποιείτε τη συσκευή σας, τόσο περισσότερο θα εμφανίζουμε τα πρόσφατα αρχεία σας εδώ.","NoTopLevelSuggestions_SettingsLink":"Εκκίνηση ρυθμίσεων έναρξης.","NoTopLevelSuggestions_SettingsText":"Για να εμφανίσετε τα πρόσφατα αρχεία και τις νέες εφαρμογές σας, ενεργοποιήστε τα στις Ρυθμίσεις. "}}
