{"RecommendedArea":{"RecommendedString":"Nos recommandations"},"SubstrateRecommendations":{"TimestampNow":"Maintenant","TimestampSecondsAgo":"Il y a {{seconds}} s","TimestampMinutesAgo":"Il y a {{minutes}} m","TimestampHoursAgo":"Il y a {{hours}} h","TimestampYesterday":"Hier à {{time}}","TimeStampDayAtTime":"Le {{date}} à {{time}}"},"NoTopLevelSuggestionsText":{"NoTopLevelSuggestions_AppsAndFilesEnabled":"Plus vous utiliserez votre appareil, plus nous afficherons vos fichiers récents et vos nouvelles applications ici.","NoTopLevelSuggestions_AppsEnabled":"Plus vous utiliserez votre appareil, plus nous afficherons vos nouvelles applications ici.","NoTopLevelSuggestions_FilesEnabled":"Plus vous utiliserez votre appareil, plus nous afficherons vos fichiers récents ici.","NoTopLevelSuggestions_SettingsLink":"Lancer les paramètres de démarrage.","NoTopLevelSuggestions_SettingsText":"Pour afficher vos fichiers récents et les nouvelles applications, activez-les dans Paramètres. "}}
