<?xml version="1.0" encoding="utf-8"?>
<WindowsEditions xmlns:e="urn:schemas-microsoft-com:windows:editions:v1">
	<Edition>
		<Name>CoreN</Name>
	</Edition>
	<Edition>
		<Name>CoreCountrySpecific</Name>
	</Edition>
	<Edition virtual="true">
		<Name>CoreSingleLanguage</Name>
		<ParentEdition>Core</ParentEdition>
	</Edition>
	<Edition>
		<Name>Core</Name>
	</Edition>
	<Edition virtual="true">
		<Name>CloudEditionN</Name>
		<ParentEdition>ProfessionalN</ParentEdition>
	</Edition>
	<Edition>
		<Name>ProfessionalN</Name>
	</Edition>
	<Edition virtual="true">
		<Name>CloudEdition</Name>
		<ParentEdition>Professional</ParentEdition>
	</Edition>
	<Edition>
		<Name>Professional</Name>
	</Edition>
	<Edition>
		<Name>EnterpriseGN</Name>
	</Edition>
	<Edition virtual="true">
		<Name>EnterpriseN</Name>
		<ParentEdition>ProfessionalN</ParentEdition>
	</Edition>
	<Edition>
		<Name>EnterpriseNEval</Name>
	</Edition>
	<Edition virtual="true">
		<Name>IoTEnterpriseS</Name>
		<ParentEdition>EnterpriseS</ParentEdition>
	</Edition>
	<Edition>
		<Name>EnterpriseS</Name>
	</Edition>
	<Edition>
		<Name>EnterpriseSEval</Name>
	</Edition>
	<Edition>
		<Name>EnterpriseSN</Name>
	</Edition>
	<Edition>
		<Name>EnterpriseSNEval</Name>
	</Edition>
	<Edition virtual="true">
		<Name>ProfessionalEducation</Name>
		<ParentEdition>Professional</ParentEdition>
	</Edition>
	<Edition virtual="true">
		<Name>ProfessionalEducationN</Name>
		<ParentEdition>ProfessionalN</ParentEdition>
	</Edition>
	<Edition virtual="true">
		<Name>ProfessionalWorkstation</Name>
		<ParentEdition>Professional</ParentEdition>
	</Edition>
	<Edition virtual="true">
		<Name>ProfessionalWorkstationN</Name>
		<ParentEdition>ProfessionalN</ParentEdition>
	</Edition>
	<Edition virtual="true">
		<Name>Education</Name>
		<ParentEdition>Professional</ParentEdition>
	</Edition>
	<Edition virtual="true">
		<Name>EducationN</Name>
		<ParentEdition>ProfessionalN</ParentEdition>
	</Edition>
	<Edition>
		<Name>PPIPro</Name>
	</Edition>
	<Edition virtual="true">
		<Name>ProfessionalCountrySpecific</Name>
		<ParentEdition>Professional</ParentEdition>
	</Edition>
	<Edition virtual="true">
		<Name>ProfessionalSingleLanguage</Name>
		<ParentEdition>Professional</ParentEdition>
	</Edition>
	<Edition>
		<Name>EnterpriseG</Name>
	</Edition>
	<Edition virtual="true">
		<Name>ServerRdsh</Name>
		<ParentEdition>Professional</ParentEdition>
	</Edition>
	<Edition virtual="true">
		<Name>IoTEnterprise</Name>
		<ParentEdition>Professional</ParentEdition>
	</Edition>
	<Edition virtual="true">
		<Name>Enterprise</Name>
		<ParentEdition>Professional</ParentEdition>
	</Edition>
	<Edition>
		<Name>EnterpriseEval</Name>
	</Edition>
	<Edition>
		<Name>Starter</Name>
	</Edition>
	<Edition>
		<Name>StarterN</Name>
	</Edition>
</WindowsEditions>
